search_engine_tool_vito/__init__.py
search_engine_tool_vito/search_engine_tool.py
search_engine_tool_vito/engine/__init__.py
search_engine_tool_vito/engine/bing.py
search_engine_tool_vito/engine/google.py
search_engine_tool_vito/engine/yahoo.py
search_engine_tool_vito_0.3.0-0.3.0.dist-info/LICENSE
search_engine_tool_vito_0.3.0-0.3.0.dist-info/METADATA
search_engine_tool_vito_0.3.0-0.3.0.dist-info/WHEEL
search_engine_tool_vito_0.3.0-0.3.0.dist-info/top_level.txt
search_engine_tool_vito_0.3.0-0.3.0.dist-info/RECORD
